notebookutils/__init__.py
notebookutils/credentials.py
notebookutils/fabricClient.py
notebookutils/fs.py
notebookutils/lakehouse.py
notebookutils/notebook.py
notebookutils/runtime.py
notebookutils/session.py
notebookutils/warehouse.py
notebookutils/workspace.py
notebookutils/mssparkutils/__init__.py
notebookutils/mssparkutils/credentials.py
notebookutils/mssparkutils/env.py
notebookutils/mssparkutils/fs.py
notebookutils/mssparkutils/lakehouse.py
notebookutils/mssparkutils/notebook.py
notebookutils/mssparkutils/runtime.py
notebookutils/mssparkutils/session.py
notebookutils/mssparkutils/handlers/__init__.py
notebookutils/mssparkutils/handlers/fsHandler.py
notebookutils_interface-0.2.2.dist-info/METADATA
notebookutils_interface-0.2.2.dist-info/WHEEL
notebookutils_interface-0.2.2.dist-info/top_level.txt
notebookutils_interface-0.2.2.dist-info/RECORD
