Metadata-Version: 2.1
Name: notebookutils-interface
Version: 0.2.2
Summary: A short description of your project.
Author: The Scripting Guy
Project-URL: repository, https://github.com/TheScriptingGuy/notebookutils-interface
Keywords: notebookutils,Synapse,Fabric
Classifier: Programming Language :: Python :: 3
Classifier: License :: OSI Approved :: MIT License
Classifier: Operating System :: OS Independent
Requires-Python: >=3.6
Requires-Dist: numpy
Requires-Dist: pyarrow <=16.0.0,>=9
Requires-Dist: fsspec
